djangoFCM/__init__.py
djangoFCM/admin.py
djangoFCM/apps.py
djangoFCM/tasks.py
djangoFCM/admin/__init__.py
djangoFCM/admin/models/__init__.py
djangoFCM/admin/models/application.py
djangoFCM/admin/models/notification.py
djangoFCM/admin/models/push_token.py
djangoFCM/fields/__init__.py
djangoFCM/forms/__init__.py
djangoFCM/forms/data_composer.py
djangoFCM/locale/ru_RU/LC_MESSAGES/django.po
djangoFCM/migrations/0001_initial.py
djangoFCM/migrations/0002_auto_20220111_1251.py
djangoFCM/migrations/__init__.py
djangoFCM/models/__init__.py
djangoFCM/models/application/__init__.py
djangoFCM/models/application/manager.py
djangoFCM/models/application/model.py
djangoFCM/models/notification/__init__.py
djangoFCM/models/notification/manager.py
djangoFCM/models/notification/model.py
djangoFCM/models/push_token/__init__.py
djangoFCM/models/push_token/manager.py
djangoFCM/models/push_token/model.py
djangoFCM/src/__init__.py
djangoFCM/src/fcm.py
djangoFCM/static/djangoFCM/generic/css/data-composer.css
djangoFCM/static/djangoFCM/generic/js/data-composer.js
djangoFCM/templates/djangoFCM/admin/recipients_composer.html
djangoFCM/templates/djangoFCM/generic/data-composer.html
djangoFCM-0.3.0.dist-info/LICENSE
djangoFCM-0.3.0.dist-info/METADATA
djangoFCM-0.3.0.dist-info/WHEEL
djangoFCM-0.3.0.dist-info/top_level.txt
djangoFCM-0.3.0.dist-info/RECORD
