Metadata-Version: 2.1
Name: djangoFCM
Version: 0.3.0
Summary: Django app which stores, manages FCM push tokens and interacts with them.
Home-page: https://github.com/omelched/djangoFCM
Author: Denis Omelchenko
Author-email: omelched@gmail.com
License: UNKNOWN
Project-URL: Bug Tracker, https://github.com/omelched/djangoFCM/issues
Project-URL: Changelog, https://github.com/omelched/djangoFCM/releases
Platform: UNKNOWN
Classifier: Development Status :: 3 - Alpha
Classifier: Environment :: Web Environment
Classifier: Framework :: Django
Classifier: Framework :: Django :: 3.2
Classifier: Intended Audience :: Developers
Classifier: License :: OSI Approved :: GNU Affero General Public License v3
Classifier: License :: OSI Approved :: GNU Affero General Public License v3 or later (AGPLv3+)
Classifier: Operating System :: OS Independent
Classifier: Natural Language :: English
Classifier: Natural Language :: Russian
Classifier: Operating System :: OS Independent
Classifier: Programming Language :: Python
Classifier: Programming Language :: Python :: 3
Classifier: Programming Language :: Python :: 3.8
Classifier: Programming Language :: Python :: 3.9
Classifier: Programming Language :: Python :: 3.10
Classifier: Topic :: Database
Classifier: Topic :: Internet
Classifier: Topic :: Internet :: WWW/HTTP
Classifier: Topic :: Utilities
Requires-Python: >=3.8
License-File: LICENSE
Requires-Dist: django (>=3.2.8)
Requires-Dist: django-celery-beat (>=2.2.1)
Requires-Dist: pyfcm (>=1.5.4)
Requires-Dist: django-picklefield (>=3.0.1)
